{
    "32524": {
        "<if_woman>「姉ちゃん……　姉ちゃーん……！<else>「兄ちゃん……　兄ちゃーん……！<endif>": "<if_woman>>Grande soeur... Grande soeur... !<else>>Grand frere... Grand frere... ! <endif>"
    },
    "32525": {
        "<if_woman>「あっ　姉ちゃん！\n　こんな所に　いたんだ？<else>「あっ　兄ちゃん！\n　こんな所に　いたんだ？<endif>": "<if_woman>>Ah, grande soeur ! Tu etais ici ?<else>>Ah, grand frere ! Tu etais ici ? <endif>"
    },
    "32526": {
        "「よかった。\n　ちっちゃいアバさまの　言ったとおりだ。\n　……思いって　ちゃんと届くんだね！": "C'est super. La petite Abba-sama avait raison.\n...Les sentiments parviennent vraiment a\ndestination !"
    },
    "32527": {
        "<if_woman>「おいら　姉ちゃんに　これを届けにきたんだよ。<else>「おいら　兄ちゃんに　これを届けにきたんだよ。<endif>": "<if_woman>>Je suis venu apporter ca a ma\ngrande soeur.<else>>Je suis venu apporter ca a mon grand frere.<endif>"
    },
    "32528": {
        "<pc>は\nごきげんなぼうしを　手に入れた！<me 60>": "<pc> a obtenu le Chapeau Joyeux ! <me\n60>"
    },
    "32529": {
        "<if_woman>「せっかく　作ってあげたのに\n　忘れていったでしょ？\n　ホント　姉ちゃんは　おっちょこちょいだなあ。<else>「せっかく　作ってあげたのに\n　忘れていったでしょ？\n　ホント　兄ちゃんは　おっちょこちょいだなあ。<endif>": "<if_woman>>Je me suis donne la peine de le\nfaire pour toi, mais tu l'as oublie, n'est-ce\npas ? Franchement, grande soeur, tu es vraiment<br>tete en l'air.<else>>Je me suis donne la peine de le faire pour\ntoi, mais tu l'as oublie, n'est-ce pas ?\nFranchement, grand frere, tu es vraiment tete<br>en l'air. <endif>"
    },
    "32530": {
        "「……今まで　ありがとう。\n　迷惑ばっかりかけて　ごめんね。": "...Merci pour tout jusqu'a present. Je suis\ndesole de t'avoir cause tant de soucis."
    },
    "32531": {
        "<if_woman>「大好きだよ……　姉ちゃん！！<else>「大好きだよ……　兄ちゃん！！<endif>": "<if_woman>>Je t'adore... grande soeur !!<else>>Je t'adore... grand frere !!<endif>"
    },
    "32532": {
        "「おーい……　おーい……！": "He... he... !"
    },
    "32533": {
        "「ねえ……　ちょっとー……！": "He... un instant... !"
    },
    "32534": {
        "<if_woman>「お姉ちゃん……　お姉ちゃーん……！<else>「お兄ちゃん……　お兄ちゃーん……！<endif>": "<if_woman>> Grande soeur... Grande soeur... !<else>> Grand frere... Grand frere... ! <endif>"
    },
    "32535": {
        "「あっ　お前！\n　こんな所に　いやがったのか？": "Ah, toi ! Tu etais ici, dans un endroit pareil\n?"
    },
    "32536": {
        "「あっ！\n　あんた　こんな所に　いたのね？": "Ah ! Tu etais ici, toi ?"
    },
    "32537": {
        "<if_woman>「あっ　お姉ちゃん！\n　こんな所に　いたんだ～？<else>「あっ　お兄ちゃん！\n　こんな所に　いたんだ～？<endif>": "<if_woman>>Ah, grande soeur ! Tu etais ici ?<else>>Ah, grand frere ! Tu etais la ? <endif>"
    },
    "32538": {
        "「よかった。\n　ちっちゃいアバさまの　言ったとおりだぜ。\n　……思いって　ちゃんと届くんだな！": "C'est super. La petite Abba-sama avait raison.\n...Les sentiments parviennent vraiment a\ndestination !"
    },
    "32539": {
        "「よかったわ。\n　ちっちゃいアバさまの　言ったとおりね。\n　……思いって　ちゃんと届くんだ！": "C'est super. Comme l'avait dit la petite\nAbba-sama. ... Les sentiments parviennent\nvraiment a destination !"
    },
    "32540": {
        "「よかった。\n　ちっちゃいアバさまの　言ったとおりだよ。\n　……思いって　ちゃんと届くんだね！": "Je suis content. C'etait exactement comme la\npetite Abba-sama l'avait dit. ...Les pensees\nparviennent vraiment a destination, n'est-ce<br>pas !"
    },
    "32541": {
        "「オレは　お前に　これを届けにきたんだ。": "Je suis venu te remettre ceci."
    },
    "32542": {
        "「あたし　あんたに　これを届けにきたのよ。": "Je suis venu te remettre ceci."
    },
    "32543": {
        "<if_woman>「私　お姉ちゃんに　これを届けにきたんだよ。<else>「私　お兄ちゃんに　これを届けにきたんだよ。<endif>": "<if_woman>>Je suis venue apporter ca a ma\ngrande soeur.<else>>Je suis venu apporter ca a mon grand frere.<endif>"
    },
    "32544": {
        "「オレが　せっかく　作ってやったのに\n　忘れていっただろ？\n　ホント　お前は　おっちょこちょいだなあ。": "Je t'ai fait ca avec tant de soin, et tu l'as\noublie, non ? Franchement, tu es vraiment tete\nen l'air."
    },
    "32545": {
        "「せっかく　作ってあげたのに\n　忘れていったでしょ？\n　あんたって　ホント　おっちょこちょいよね！": "Je l'avais fait expres pour toi, et tu l'as\noublie, n'est-ce pas ? Tu es vraiment tete en\nl'air !"
    },
    "32546": {
        "<if_woman>「せっかく　作ってあげたのに\n　忘れていったでしょ？　お姉ちゃんって\n　ホント　おっちょこちょいなんだから～。<else>「せっかく　作ってあげたのに\n　忘れていったでしょ？　お兄ちゃんって\n　ホント　おっちょこちょいなんだから～。<endif>": "<if_woman>>Je l'ai fait expres pour toi et tu\nl'as oublie, n'est-ce pas ? Grande soeur, tu es\nvraiment tete en l'air...<else>>Je l'ai fait expres pour toi et tu l'as\noublie, n'est-ce pas ? Grand frere, tu es\nvraiment tete en l'air... <endif>"
    },
    "32547": {
        "「……今まで　ありがとうな。\n　迷惑ばっかりかけて　悪かったよ。": "......Merci pour tout jusqu'a maintenant. Je\nsuis desole d'avoir cause tant de soucis."
    },
    "32548": {
        "「……今まで　ありがと。\n　いっぱい迷惑かけて　悪かったわね。": "Merci pour tout jusqu'a present. Je suis\ndesolee de t'avoir cause tant de soucis."
    },
    "32549": {
        "「……今まで　ありがとう。\n　いっぱい迷惑かけちゃって　ごめんね。": "Merci pour tout jusqu'a present. Je suis\ndesole de t'avoir cause tant de problemes."
    },
    "32550": {
        "「お前のこと……　ずっと　忘れないからな！！": "Je ne t'oublierai jamais !!"
    },
    "32551": {
        "「あんたのこと……　絶対　忘れないからっ！！": "Je ne t'oublierai jamais !!"
    },
    "32552": {
        "<if_woman>「大好きだよ……　お姉ちゃん！！<else>「大好きだよ……　お兄ちゃん！！<endif>": "<if_woman>>Je t'adore... grande soeur !!<else>>Je t'adore... grand frere !! <endif>"
    },
    "65024": {
        "「とうとう　目覚めてしまいましたか……。": "Vous vous etes enfin eveille..."
    },
    "65025": {
        "「闇の底より来たる　災いの王……！": "Le roi des calamites venu des profondeurs des\ntenebres... !"
    },
    "65026": {
        "「滅びの運命は　時を刻み始めました……。": "Le destin de la destruction a commence a se\nprofiler..."
    },
    "65027": {
        "「私はここで　戦う意志を持つ者を待ちましょう。\n　あなたたちは　五大陸の　王の所へおもむき\n　成すべきことを　伝えなさい。": "Je vais attendre ici ceux qui ont la volonte\nde se battre. Vous, allez voir les rois des\ncinq continents et transmettez-leur ce qui<br>doit etre fait."
    }
}