{
    "6793": {
        "「旅の者よ。城に入るのは　しばし待たれよ。": "Voyageur, veuillez patienter un moment avant\nd'entrer dans le chateau."
    },
    "6794": {
        "「今から　女王ディオーレさまが\n　恵みの歌を　お唄いになられるところだ。\n　旅の記念に　ぜひ聴いていくがよい。": "A present, la Reine Diore va chanter le Chant\nde la Benediction. En souvenir de votre\nvoyage, prenez le temps d'ecouter."
    },
    "6795": {
        "<center>\n……海に生まれ　海に生きる。\nそれが我ら　ウェディの民。": "...Nes dans la mer, nous vivons dans la mer.\nTelle est la vie de notre peuple, les Weddies."
    },
    "6796": {
        "<center>\n大いなる海の神よ。\n我らの命　我らの思い\n守りたまえ　清めたまえ……。": "O grand dieu de la mer, Protege nos vies,\npurifie nos esprits..."
    },
    "6797": {
        "「あの歌は　恵みの歌と言ってな。\n　この辺りの水という水に　聖なる加護を\n　与えてくれる　ありがたいものなんだよ。": "Cette chanson est appelee la chanson de la\nbenediction. Elle confere une protection\nsacree a toutes les eaux de cette region.<br>C'est une chose precieuse."
    },
    "6798": {
        "「女王ディオーレさまは　相変わらず\n　氷のような冷たい　お顔をしておられる。": "La Reine Diore sama arbore toujours ce visage\naussi froid que la glace."
    },
    "6799": {
        "「女王には息子……つまり　王子がいてな。\n　ふたりの仲が　うまくいってないという\n　ウワサがあるんだ。": "La reine a un fils... c'est-a-dire, un prince.\nIl y a des rumeurs selon lesquelles leur\nrelation n'est pas au beau fixe."
    },
    "6801": {
        "「この国じゃ　女が王位を継ぐのが\n　ならわしに　なっているからな。\n　いろいろ　あるんだろうさ……。": "Dans ce pays, il est de coutume que ce soit\nune femme qui herite du trone. Il doit y avoir\ntoutes sortes de raisons a cela..."
    },
    "6802": {
        "「おっと。旅の者に言うことじゃなかったな。\n　今のは　忘れてくれ。": "Oups. Ce n'etait pas quelque chose a dire a un\nvoyageur. Oublie ce que je viens de dire."
    },
    "6803": {
        "「ふふふ……。もうすぐ私の時代が来るわ！": "Fufufu... Mon epoque est sur le point\nd'arriver !"
    },
    "6804": {
        "「テキスト削除": "texte supprimer"
    },
    "6805": {
        "「あひゃっ！": "Ah ah !"
    },
    "6806": {
        "「グルルゥ……。\n　ギャワンギャワン！": "Gruuuu... Gyaou Gyaou !"
    },
    "6807": {
        "「痛い　痛いっ。": "Aie, aie !"
    },
    "6808": {
        "「うひぃっ。": "Ouh la !"
    },
    "6809": {
        "「母上。なぜ　禁断の地の存在を\n　僕に　教えてくれなかったのですか？　": "Mere. Pourquoi ne m'avez-vous pas parle de\nl'existence de la Terre Interdite ?"
    },
    "6810": {
        "「必要がない。": "Il n'est pas necessaire."
    },
    "6811": {
        "「僕は　この国の王子。\n　国のすべてを　知っている必要があります。": "Je suis le prince de ce royaume. Je dois tout\nsavoir sur le pays."
    },
    "6812": {
        "「……知れば　理解したと考えるか。\n　それが　浅はかだというのだ。": "...Penses-tu avoir compris simplement parce\nque tu sais quelque chose ? C'est cela que\nl'on appelle de la superficialite."
    },
    "6813": {
        "「知ることができなければ　浅はかかどうかを\n　判断することも　できないでしょう。\n　禁断の地のことを　僕に　教えてください。": "Si je ne peux pas savoir, comment pourrais-je\njuger si c'est insense ou non ? Veuillez\nm'apprendre ce qu'il en est de la Terre<br>Interdite."
    },
    "6814": {
        "「必要ないと言った！": "J'ai dit que ce n'etait pas necessaire !"
    },
    "6815": {
        "「ま　まあまあ　落ち着いて。": "Ma... ma... Calmons-nous."
    },
    "6816": {
        "「オーディスも　もう子供ではない。\n　いろいろと考えてるのだよ　ディオーレ。\n　だから　その……。": "Odys n'est plus un enfant. Il reflechit a\nbeaucoup de choses, tu sais, Dioray. C'est\npourquoi..."
    },
    "6817": {
        "「君は　旅の人のようだな。\n　僕の名は　オーディス。\n　このヴェリナード王国の王子だ。": "Tu sembles etre un voyageur. Mon nom est\nAudis. Je suis le prince de ce royaume de\nVerinard."
    },
    "6818": {
        "「……もしや　君は一人前の証を得て\n　旅をしているんじゃないか？<yesno><close>": "Peut-etre as-tu obtenu la preuve que tu es\ndevenu un aventurier accompli et que tu\nvoyages ?<yesno><close>"
    },
    "6819": {
        "「これは　僕にとって重要なことなんだ。\n　君が　一人前の証を持っているなら\n　正直に　そうだと答えてくれないか？<yesno><close>": "Pour moi, c'est quelque chose d'important. Si\ntu as la preuve que tu es un aventurier\naccompli, peux-tu repondre honnetement par un<br>oui ou un non ?<yesno><close>"
    },
    "6820": {
        "「やはり　そうか……。\n　彼女の言うことが　また当たった。": "Comme je le pensais... Ce que Her a dit s'est\nencore avere vrai."
    },
    "6821": {
        "「この後　城内にある　調査団の詰所まで\n　足を運んでくれないだろうか。": "Pourrais-tu te rendre au poste de la mission\nd'enquete situe dans le chateau apres cela ?"
    },
    "6822": {
        "「場所は　城の者に聞けば　すぐわかる。\n　よろしく頼む！": "Si tu demandes a quelqu'un du chateau, tu\ntrouveras facilement l'emplacement. Je compte\nsur toi !"
    },
    "6823": {
        "「旅の者よ　よくぞ来た。\n　こちらにおわすのが　ヴェリナード王国を\n　治める女王　ディオーレさまだ。": "Voyageur, te voila enfin. Voici Sa Majeste la\nReine D'Oray, souveraine du royaume de\nVelinard."
    },
    "6824": {
        "「ちなみに　ワシは　そのダンナだ。\n　メルー公と呼んでくれ。よろしくな。": "Au fait, je suis le mari. Appelle-moi Lord\nMeru. Enchante."
    },
    "6825": {
        "「わらわは　恵みの歌を終え\n　疲れておるのだ。": "Je viens de terminer le chant de benediction\net je suis epuisee."
    },
    "6826": {
        "「……旅の者と話すことなどない。\n　引き取るがいい。": "Je n'ai rien a dire a un voyageur. Tu ferais\nmieux de partir."
    },
    "6827": {
        "「すまんな　旅の者よ。そういうわけなのだ。": "Je suis desole, voyageur. C'est ainsi que les\nchoses sont."
    },
    "6828": {
        "「……女王と王子の仲が　こじれていてな。\n　いやはや　困ったものなのだよ。": "......La relation entre la reine et le prince\nest tendue. Ah, c'est vraiment problematique."
    },
    "6829": {
        "「当の王子は　王立調査団に入りびたりで\n　ワシの話を聞こうともせぬし……。": "Le prince en question passe tout son temps\navec l'equipe royale d'exploration et ne\ndaigne meme pas ecouter ce que j'ai a dire..."
    },
    "6830": {
        "「おお　そうだ。よければ　王立調査団の所に行き\n　王子の　話し相手になってやってくれんか。\n　旅の者の話を聞くのも　よい勉強だ。": "Oh, c'est vrai. Si cela ne te derange pas,\npourrais-tu te rendre au camp de la Commission\nRoyale et tenir compagnie au prince ? Ecouter<br>les recits d'un voyageur est toujours une\nbonne lecon."
    },
    "6831": {
        "「む　そなたは　さきほどの旅の者か。": "Oh, vous etes le voyageur de tout a l'heure ?"
    },
    "6832": {
        "「女王は　お疲れだ。\n　話があるなら　またにしてほしい。": "La reine est fatiguee. Si tu as quelque chose\na lui dire, reviens une autre fois, je te\nprie."
    },
    "6833": {
        "「王子ならば　城の２階にある\n　王立調査団の詰所へ行っているはず。\n　よければ　話し相手になってやってくれ。": "Si tu cherches le prince, il devrait etre au\nbureau de la Commission royale situe au\ndeuxieme etage du chateau. Si tu le souhaites,<br>va lui tenir compagnie."
    },
    "6834": {
        "「テキスト削除": "texte supprimer"
    },
    "6835": {
        "「それで　王子が何か困っているようなら\n　そなたのチカラを　貸してやってほしい。\n　すまんが頼んだぞ　旅の者よ。": "Si le prince semble avoir des ennuis, je te\nserais reconnaissant de bien vouloir lui\npreter main forte. Je compte sur toi,<br>voyageur."
    },
    "6836": {
        "「そうか……。永遠の水について\n　新たに　わかったことは　なかったか。": "Je vois... N'as-tu rien appris de nouveau au\nsujet de l'Eau Eternelle ?"
    },
    "6837": {
        "「はい　オーディス王子。\n　お役に立てず　申し訳ありません。": "Oui, Prince Odis. Je suis desole de ne pas\navoir pu vous etre utile."
    },
    "6838": {
        "「君が　気に病む必要はない。\n　僕の個人的な依頼に　応じてくれて\n　感謝しているよ　キンナー調査員。": "Tu n'as pas besoin de t'en faire. Je te\nremercie d'avoir repondu a ma demande\npersonnelle, Detective Kinner."
    },
    "6839": {
        "「来てくれたか　旅の人。\n　さあ　こちらへ。": "Tu es venu, voyageur. Allez, par ici."
    },
    "6840": {
        "「……ふむ。\n　君は　<pc>君というのか。": "…Hmm. Alors, tu t'appelles <pc>-kun."
    },
    "6841": {
        "「レーンの村の出身なんだな。\n　残念ながら　僕は行ったことがないが\n　よい所だと　聞いている。": "Tu viens du village de L'Aisne, n'est-ce pas ?\nMalheureusement, je n'y suis jamais alle, mais\non m'a dit que c'est un endroit agreable."
    },
    "6842": {
        "「やや？　あなたは　もしや\n　あのときの　<pc>さん？": "Oh ? Seriez-vous par hasard <pc>-san de\ncette fois-la ?"
    },
    "6843": {
        "「いつぞやの　知恵の眠る遺跡では\n　たいへん　お世話になりました。": "Je vous suis tres reconnaissant pour l'aide\nprecieuse que vous m'avez apportee lors de\nnotre passage aux Ruines de la Sagesse<br>Endormie."
    },
    "6844": {
        "「む？　ふたりは知り合いだったのか？": "Hum ? Vous vous connaissiez deja tous les deux\n?"
    },
    "6845": {
        "「説明しましょう！": "Laissez-moi vous expliquer !"
    },
    "6846": {
        "「<pc>さんには　ジュレー島での\n　遺跡調査を　手伝っていただいたのです！": "M. <pc> nous a aides avec les recherches\narcheologiques sur l'ile de Juret !"
    },
    "6847": {
        "「<pc>さんは　頼りになる方。\n　王子のチカラにも　なっていただけること\n　まちがいなし！": "<pc>-san est quelqu'un sur qui on peut\ncompter. Il sera sans aucun doute une aide\nprecieuse pour le prince !"
    },
    "6849": {
        "「では　王子。\n　別件の調査に　戻りますので\n　私は　これにて失礼いたします。": "Alors, Prince. Je vais retourner a une autre\nmission d'enquete, je vous laisse donc ici."
    },
    "6850": {
        "「ああ　すまなかった　キンナー調査員。\n　また何かあったら　声をかけよう。": "Ah, desole, Detective Kinner. Si quelque chose\nse passe a nouveau, je vous ferai signe."
    },
    "6851": {
        "「かしこまりました。": "Bien compris."
    },
    "6852": {
        "「君に来てもらったのには　理由がある。\n　まずは　彼女を紹介しよう。": "Il y a une raison pour laquelle je t'ai\ndemande de venir. Tout d'abord, laisse-moi te\npresenter Her."
    },
    "6853": {
        "「キャスランだ。": "C'est Cathlan."
    },
    "6854": {
        "「はじめまして。旅の占い師をしておりますわ。\n　王子さまのお役に立てとの　占いに従い　\n　この城へ　参りましたの。": "Enchantee de faire votre connaissance. Je suis\nune voyante itinerante. Suivant une prediction\nqui m'indiquait d'aider le prince, je suis<br>venue en ce chateau."
    },
    "6855": {
        "「彼女の占いは　すばらしい。\n　すでに　ふたつの事実を言い当てている。\n　ひとつは　君のことだ。": "La divination de Her est incroyable. Elle a\ndeja predit deux faits. L'un d'eux te\nconcerne."
    },
    "6856": {
        "「白亜の城に　一人前の証を持つ　旅人ひとり。\n　王子は　その者と共に目的を果たさん……。": "Un voyageur portant la preuve de sa competence\nse dirige vers le chateau d'albatre. Le prince\naccomplira son objectif avec cette personne..."
    },
    "6858": {
        "「キャスランは　もうひとつの占いで\n　禁断の地として　隠されていた\n　永遠の地下迷宮の存在を　教えてくれた。": "Cathlan m'a revele l'existence du Labyrinthe\nde l'Eternite, un lieu interdit cache par une\nautre prophetie."
    },
    "6859": {
        "「そして　その永遠の地下迷宮には\n　おどろくべきものが　隠されていたんだ。": "Et dans ce Labyrinthe de l'Eternite, quelque\nchose de stupefiant etait dissimule."
    },
    "6860": {
        "「クチで説明するよりも　君にも\n　その目で　見てもらいたい。\n　永遠の地下迷宮まで　来てくれないか？　": "Plutot que de te l'expliquer, j'aimerais que\ntu le voies de tes propres yeux. Peux-tu venir\njusqu'au Labyrinthe de l'Eternite ?"
    },
    "6861": {
        "「永遠の地下迷宮は　このヴェリナード城を\n　北に行った場所にあるんだ。\n　くわしいことは　調査員に聞くといい。　": "Le Labyrinthe de l'Eternite se trouve au nord\nde ce Chateau de Verinard. Pour plus de\ndetails, tu devrais demander aux enqueteurs."
    },
    "6862": {
        "「それでは　僕は　キャスランと共に\n　先に　永遠の地下迷宮へと向かっている。\n　必ず　来てくれ　<pc>君。": "Alors, je pars en avant avec Cathlan vers le\nLabyrinthe de l'Eternite. Assure-toi de venir,\n<pc>-kun."
    },
    "6863": {
        "「テキスト削除": "texte supprimer"
    },
    "6864": {
        "「早かったな　<pc>君。": "Tu es rapide, <pc>-kun."
    },
    "6865": {
        "「この扉のカギは　僕が持っている。\n　このカギを見つけたのも\n　キャスランの占いの　おかげなんだ。": "J'ai la cle de cette porte. C'est grace a la\ndivination de Cathlan que j'ai trouve cette\ncle."
    },
    "6866": {
        "「よし　入ってくれ　<pc>君。": "Bien, entre, <pc>-kun."
    },
    "6867": {
        "「……見てほしい　この女性を。\n　彼女は　死んでいるわけじゃない。": "...Regarde cette femme. Elle n'est pas morte."
    },
    "6868": {
        "「この水は　永遠の水というものだ。\n　調査の結果　中に入ったものの時の流れを\n　止めてしまうチカラがあると　わかった。": "Cette eau est appelee l'eau eternelle. Les\nrecherches ont revele qu'elle possede le\npouvoir d'arreter le cours du temps pour ceux<br>qui y entrent."
    },
    "6869": {
        "「つまり　彼女は囚われているんだ。\n　生きたまま　この水の柱の中に……。": "En d'autres termes, Her est prisonniere.\nVivante, a l'interieur de ce pilier d'eau..."
    },
    "6870": {
        "「この女性の存在を　隠すために\n　ここは　禁断の地とされたのでしょう。": "Il est probable que cet endroit ait ete\ndesigne comme terre interdite pour dissimuler\nl'existence de cette femme."
    },
    "6871": {
        "「私の占いによれば　この女性は\n　高貴な血を持つお方と　出ています。\n　おそらくは　ヴェリナード王家の……。": "Selon ma divination, cette femme possede un\nsang noble. C'est probablement lie a la\nfamille royale de Velinard..."
    },
    "6872": {
        "「きっと　何かの事件に巻き込まれ\n　このような目に……おいたわしや。": "Surement, il a ete pris dans un incident\nquelconque et c'est ainsi qu'il s'est retrouve\ndans cette situation... Pauvre de lui."
    },
    "6873": {
        "「その占いを聞いて　城の中を調べさせたら\n　いつ書かれたのかも　わからない\n　古い書物が見つかった。": "Apres avoir ecoute cette prediction et fait\nfouiller le chateau, un vieux livre dont on\nignore la date de redaction a ete decouvert."
    },
    "6874": {
        "「そこには　ひとりの王女が\n　行方知れずになったと　書かれていたよ。\n　とても　偶然とは思えない。": "Il etait ecrit qu'une princesse avait disparu.\nCa ne peut pas etre une simple coincidence."
    },
    "6875": {
        "「彼女は　我が王家の一族なんだ。\n　だから僕は　彼女を助けようと思う。": "Her fait partie de notre famille royale. C'est\npourquoi j'ai decide de l'aider."
    },
    "6876": {
        "「だが　この永遠の水をなんとかしない限り\n　彼女に近づくことすら　できないんだ。": "Mais tant que nous ne faisons rien contre\ncette eau eternelle, nous ne pourrons meme pas\nnous approcher de Her."
    },
    "6877": {
        "「占いが示した　<pc>君が　ここに来れば\n　何かが　起こるかもしれないと思ったが……\n　残念ながら　何も　起こらないようだな。": "L'horoscope avait indique que si\n<pc>-kun venait ici, quelque chose\npourrait se produire... Mais malheureusement,<br>on dirait que rien ne se passe."
    },
    "6878": {
        "「あきらめてはいけません　王子さま。\n　今こそ　新たな占いをしてみましょう。": "Ne perdez pas espoir, Prince-sama. C'est le\nmoment de consulter a nouveau les augures."
    },
    "6879": {
        "「そうだな。今は　どんなことでも\n　手がかりが　ほしい。\n　やってみてくれるか　キャスラン。": "Oui, c'est vrai. Actuellement, nous avons\nbesoin de n'importe quel indice. Pourrais-tu\nessayer, Cathlan ?"
    },
    "6880": {
        "「では　さっそく……。": "Alors, sans plus tarder..."
    },
    "6881": {
        "「ウラウラウラウラーーーッ！": "Ura Ura Ura Uraaaaa !"
    },
    "6882": {
        "「占いたーまえ　ひらめきたーまえ。\n　ウラウラッ　ウララッ！": "O divination, revele-moi ton inspiration. Oula\noula ! Oulala !"
    },
    "6883": {
        "「ウッ！": "Ouf !"
    },
    "6884": {
        "「……出ましたわ。": "...C'est sorti."
    },
    "6885": {
        "「王家の者の唄う　刹那の歌が\n　眠った時を　目覚めさせるだろう……。": "Le chant ephemere entonne par un membre de la\nfamille royale eveillera le temps endormi..."
    },
    "6886": {
        "「王家の者……。刹那の歌……。": "La lignee royale... Le Chant de l'Ephemere..."
    },
    "6887": {
        "「刹那の歌とは　なんだ……。\n　恵みの歌と　同じようなものなのか？": "Qu'est-ce que le chant de l'instant... ?\nEst-ce quelque chose de similaire au chant de\nla grace ?"
    },
    "6888": {
        "「歌のことなら　母上が\n　何かを知っているかもしれないな……。": "Si c'est au sujet de la chanson, ma mere\npourrait savoir quelque chose..."
    },
    "6889": {
        "「僕は　母上の所に行ってくる。\n　刹那の歌のことを　聞きだしてこよう。": "Je vais aller voir ma mere. Je vais essayer\nd'en savoir plus sur la chanson de Setsuna."
    },
    "6890": {
        "「母上。刹那の歌のことを教えてください。": "Mere, s'il vous plait, parlez-moi de la\nchanson de Setsuna."
    },
    "6891": {
        "「なぜ　お前が　刹那の歌の存在を知っている？": "Pourquoi connais-tu l'existence de la chanson\nde Setsuna ?"
    },
    "6892": {
        "「やはり　母上も　禁断の地に囚われた女性が\n　刹那の歌で救えることを　知っているのですね。": "Vous savez donc aussi, Mere, que la femme\nemprisonnee dans la Terre Interdite peut etre\nsauvee par le Chant de l'Ephemere."
    },
    "6893": {
        "「刹那の歌は　我が王家に伝わる歌。\n　１０００年の間　唄うことを禁じられた歌だ。": "La chanson de Setsuna est une melodie\ntransmise dans notre famille royale. Elle est\ninterdite de chant depuis 1000 ans."
    },
    "6894": {
        "「王家の者として　わらわは\n　その禁を破るわけには　いかぬ！": "En tant que membre de la famille royale, je ne\npeux pas briser cet interdit !"
    },
    "6895": {
        "「あの女性も　我が王家に連なる者なのでしょう？\n　彼女は永遠の水の中で　今も生きています。\n　このまま見殺しにする　おつもりですか。": "あの女性も我が王家に連なる者なのでしょう？ Herは永遠の水の中で今も生きています\nこのまま見殺しにするおつもりですか Cette femme fait-elle aussi\npartie de notre lignee royale ? Her vit<br>toujours dans les eaux eternelles. Avez-vous\nl'intention de l'abandonner ainsi ?"
    },
    "6896": {
        "「確かに　あの娘は　王家の血を引く者。\n　だが　永遠の水から\n　解き放つことは　まかりならぬ。": "確かにあの娘は王家の血を引く者 だが、永遠の水から 解き放つことはできない"
    },
    "6897": {
        "「ふ　ふたりとも　そんなコワイ顔はやめて\n　もっと　ほがらかに　いこうじゃないか。": "Ne faites pas ces tetes effrayantes, vous\ndeux. Allons-y avec plus de gaiete."
    },
    "6898": {
        "「なあ　オーディス。お前も　もうオトナなんだ。\n　少しは　分をわきまえるということを覚え……。": "He, Odis. Tu es un adulte maintenant. Il est\ntemps d'apprendre a connaitre ta place..."
    },
    "6899": {
        "「あなたが　あまやかすから\n　オーディスが　調子に乗るのです！": "C'est parce que tu le gates qu'Odys devient\narrogant !"
    },
    "6900": {
        "「むう……。": "Mmm..."
    },
    "6901": {
        "「おおっ　謁見の者が来ておるようですな。\n　待たせては　いけません。": "Oh ! On dirait que le visiteur pour l'audience\nest arrive. Ne le faisons pas attendre."
    },
    "6902": {
        "「謁見はせぬ。引き取らせよ。": "Je n'accorderai pas d'audience. Faites-le\npartir."
    },
    "6903": {
        "「毎回すまんな　旅の者よ。\n　謁見は　また後日ということで。": "Je suis desole a chaque fois, voyageur. Nous\nremettrons l'audience a un autre jour."
    },
    "6904": {
        "「……それよりもだ。そなたは　王子に\n　チカラを　貸しているのだろう？": "...Mais plus important encore. Tu pretes bien\nta force au prince, n'est-ce pas ?"
    },
    "6905": {
        "「王子なら　また調査団の詰所に\n　こもっているだろう。\n　様子をみてやっては　くれないか？": "Le prince doit probablement etre encore\nenferme dans le poste de la mission d'enquete.\nPourriez-vous aller voir comment il va ?"
    },
    "6906": {
        "「おお　旅の者か。よく来たな。": "Oh, un voyageur ? Bienvenue."
    },
    "6907": {
        "「だが　女王は　しばらくは誰とも\n　謁見したくないと　おっしゃっておいでだ。": "Cependant, la reine a declare qu'elle ne\nsouhaitait rencontrer personne pour le moment."
    },
    "6908": {
        "「王子は　王立調査団の所へ行っているはずだ。\n　あの様子では　また何か　やらかすかもしれん。": "Le prince doit etre avec l'equipe royale\nd'exploration. Avec son comportement, il\npourrait encore faire des betises."
    },
    "6909": {
        "「何をしようとしているのかは　わからんが\n　そなたのチカラを　必要としているようだ。\n　王子の頼み　聞いてやってはくれんか。": "Je ne sais pas ce qu'il essaie de faire, mais\nil semble avoir besoin de ton aide.\nPourrais-tu repondre a la demande du prince ?"
    },
    "6910": {
        "「テキスト削除": "texte supprimer"
    },
    "6911": {
        "「すまんな　旅の者よ。\n　そういうわけなので　お引き取り願おう。": "Je suis desole, voyageur. Pour cette raison,\nje vous demanderai de partir."
    },
    "6912": {
        "「<pc>君も　聞いていたと思うが\n　母上は　刹那の歌のことを教えてくれなかった。": "<pc>-kun, tu as surement entendu aussi,\nmais Mere ne nous a pas parle de la chanson de\nSetsuna."
    },
    "6913": {
        "「もう　母上には頼らない。\n　僕が刹那の歌を唄って　彼女を救ってみせる。": "Je ne compterai plus sur ma mere. Je chanterai\nle Chant de l'Ephemere pour sauver Her."
    },
    "6914": {
        "「そのために　なんとしても\n　刹那の歌のありかを　見つけださなければ。": "Pour cela, nous devons absolument decouvrir\nl'emplacement de la chanson ephemere."
    },
    "6915": {
        "「ひとつ　お聞きしたいのですが\n　刹那の歌のことを知っている者は\n　女王さましか　おられないのでしょうか？": "Puis-je vous poser une question ? Est-ce que\nla seule personne qui connait la chanson de\nSetsuna est la reine ?"
    },
    "6916": {
        "「もしかしたら　ここの調査員の方たちも\n　何か　ご存知なのではないかと。": "Peut-etre que les enqueteurs ici presents\nsavent quelque chose."
    },
    "6917": {
        "「そうか。彼らにも　聞いてみるべきだな。": "Je vois. Il faudrait leur demander aussi."
    },
    "6918": {
        "「エリーゴ調査員！\n　ちょっと　来てくれ。": "Detective Eriego ! Viens par ici."
    },
    "6919": {
        "「ご用でありますか　王子どの。\n　小生は今　資料の整理に\n　余念がないのでありますが……。　": "Avez-vous besoin de quelque chose, Prince-dono\n? Je suis actuellement tres occupe a organiser\ndes documents..."
    },
    "6920": {
        "「君は　調査員の中でも古株だ。\n　誰よりも　多くのことを知っている。": "Tu es l'un des veterans parmi les enqueteurs.\nTu en sais plus que quiconque."
    },
    "6921": {
        "「刹那の歌という歌について\n　君が　知っていることはないか？": "A propos de la chanson Setsuna no Uta, est-ce\nque tu sais quelque chose ?"
    },
    "6922": {
        "「……小生は　存じません。\n　お役に立てず　申し訳ないであります。": "......Je ne sais pas. Je suis desole de ne pas\npouvoir vous aider."
    },
    "6923": {
        "「もし　母上に　クチ止めされているのなら\n　そんなことは　気にしないでいい。\n　知っていることを　教えてくれ。": "Si ta mere t'a demande de garder le silence,\nne t'en fais pas pour ca. Dis-moi ce que tu\nsais."
    },
    "6924": {
        "「……了解であります。": "...Compris."
    },
    "6925": {
        "「はるか北東の地。ブーナー熱帯雨林の南に\n　詩歌の遺跡という　遺跡があるのであります。": "Dans les terres lointaines au nord-est, au sud\nde la foret tropicale de Booner, se trouvent\nles ruines appelees Poetry Ruins."
    },
    "6926": {
        "「王家の方は　王位を継ぐと　そこへ向かい\n　歌を継承なさると　聞いたであります。\n　おそらくは　刹那の歌も　そこに……。": "Il parait que les membres de la famille\nroyale, lorsqu'ils accedent au trone, se\nrendent la-bas pour heriter du chant.<br>J'imagine que le Chant de l'Instant s'y trouve\negalement..."
    },
    "6927": {
        "「よくぞ教えてくれた　エリーゴ調査員。\n　ブーナー熱帯雨林……詩歌の遺跡だな？　": "Bien joue de m'avoir informe, Detective\nEriego. Booner Rainforest... Les ruines de\nPoetry, n'est-ce pas ?"
    },
    "6928": {
        "「行くつもりでありますか　王子どの？\n　ブーナー熱帯雨林は　魔物の徘徊する\n　危険な土地なのであります！": "Avez-vous l'intention d'y aller, Prince-dono ?\nLa foret de Booner est une terre dangereuse ou\nrodent des monstres !"
    },
    "6929": {
        "「……そうか　そういうことか。\n　キャスランの占いに　<pc>君の\n　協力が必要と出たのは　このためか。": "…Je vois, c'est donc ca. C'etait pour cette\nraison que la divination de Cathlan indiquait\nqu'il fallait la cooperation de<br><pc>-kun."
    },
    "6930": {
        "「<pc>君。\n　君の望みは　この国のキーエンブレムだろう？\n　ならば　それを　君に贈ることを約束する。": "<pc>-kun. Ton desir est le Key Emblem de\nce pays, n'est-ce pas ? Dans ce cas, je te\npromets de te l'offrir."
    },
    "6931": {
        "「だから　改めて頼みたい。\n　ブーナー熱帯雨林に潜む　魔物を倒して\n　僕たちの進む道を　確保してくれないか？<yesno><close>": "Donc, je veux te demander a nouveau.\nPourrais-tu vaincre les monstres qui se\ncachent dans la foret de Booner et securiser<br>notre chemin ? <yesno><close>"
    },
    "6932": {
        "「そんなことを　言わないでくれ。\n　君のチカラが必要なんだ。": "Ne dis pas ca. Nous avons besoin de ta force."
    },
    "6933": {
        "「ブーナー熱帯雨林に潜む　魔物を倒して\n　僕たちの進む道を　確保してくれないか？<yesno><close>": "Pourrais-tu vaincre les monstres qui se\ncachent dans la Foret de Booner Rainforest et\nsecuriser notre chemin ? <yesno><close>"
    },
    "6934": {
        "「おお　ありがとう　<pc>君。": "Oh, merci, <pc>-kun."
    },
    "6935": {
        "「よし　すぐに出発しよう。\n　ブーナー熱帯雨林は　この城の北東。\n　かなり　歩いた所にあったはずだ。": "D'accord, partons immediatement. La Foret de\nBooner se trouve au nord-est de ce chateau.\nC'est un endroit qui devrait etre assez loin a<br>pied."
    },
    "6936": {
        "「よくやってくれた　<pc>君。\n　君が　魔物をけちらしてくれたおかげで\n　僕たちは　安全に来ることができた。": "Bien joue, <pc>-kun. Grace a toi et a ta\ncapacite a chasser les monstres, nous avons pu\narriver en toute securite."
    },
    "6937": {
        "「ここが　エリーゴ調査員の言っていた\n　詩歌の遺跡なのだろうか。": "Est-ce ici les Ruines Poetiques dont parlait\nle detective Eriego ?"
    },
    "6938": {
        "「むっ？　あれは　なんだ？": "Mmh ? Qu'est-ce que c'est ?"
    },
    "6939": {
        "「かなり古い石碑のようだ……。\n　何か　文字が書かれているな。": "Il semble s'agir d'une stele assez ancienne...\nIl y a des inscriptions dessus."
    },
    "6940": {
        "「こ　これは……。": "Ce... ceci est..."
    },
    "6941": {
        "「この石碑には　ヴェリナード王家に\n　伝わる歌のことが　書かれている。\n　ここが詩歌の遺跡と見て　まちがいないな。": "Cette stele parle d'une chanson transmise par\nla famille royale de Verinard. Il n'y a aucun\ndoute, nous sommes bien aux Ruines de la<br>Poesie."
    },
    "6942": {
        "「だが　この石碑には　かんじんの\n　刹那の歌の内容が　書かれていない……。": "Cependant, sur cette stele, le contenu\nessentiel du Chant de l'Instant n'est pas\ninscrit..."
    },
    "6943": {
        "「手分けして　歌を探すことにしよう。\n　僕とキャスランは　南側に行ってみる。": "Divisons-nous pour chercher la chanson.\nCathlan et moi allons explorer le cote sud."
    },
    "6944": {
        "「<cs_pchero>君　何か見つかったのか？": "<cs_pchero>kun, as-tu trouve quelque chose ?"
    },
    "6945": {
        "「あの石碑は……。\n　もしや　あれが　そうなのか？": "Ce monument de pierre... Serait-ce cela ?"
    },
    "6946": {
        "「おお……。この石碑には\n　刹那の歌の内容が　書かれている。": "Oh... Sur cette stele est inscrite la chanson\nde l'instant."
    },
    "6947": {
        "「これで　僕は　刹那の歌を覚えられるぞ。": "Avec ca, je vais enfin pouvoir apprendre la\nChanson de l'Instant."
    },
    "6948": {
        "「うわっ！！": "Ouah !!"
    },
    "6949": {
        "「な……何が起こった！？": "Qu'est-ce qui s'est passe !?"
    },
    "6950": {
        "「我が名は　詩歌の守り手。\n　歌を見守り　歌を育む者なり。": "Mon nom est Elegiac Crablet. Je suis celui qui\nveille sur les chants et les cultive."
    },
    "6951": {
        "「王家に伝わりし詩歌を　求める者は\n　そのチカラを　我に示さねばならぬ。": "Ceux qui cherchent les chants transmis par la\nfamille royale doivent me montrer leur force."
    },
    "6952": {
        "「くっ　こんな番人がいるとは。": "Tch, je ne m'attendais pas a trouver un\ngardien ici."
    },
    "6953": {
        "「<cs_pchero>君　こいつの相手を頼めるか？\n　僕は　キャスランを守ろう。": "<cs_pchero>kun, pourrais-tu t'occuper de\ncelui-ci ? Je vais proteger Cathlan."
    },
    "6954": {
        "「我の相手をするのは　おぬしか。\n　ならば　そのチカラを存分に示すがよい！": "Tu es celui qui va m'affronter, n'est-ce pas ?\nMontre-moi donc toute l'etendue de ta\npuissance !"
    },
    "6955": {
        "「戻ってきてくれたか　<cs_pchero>君。": "Tu es revenu, <cs_pchero> kun."
    },
    "6956": {
        "「詩歌の守り手を　倒さない限り\n　刹那の歌を覚えることは　できない。": "Tant que tu n'auras pas vaincu l'Elegiac\nCrablet, tu ne pourras pas apprendre la\nchanson de l'instant."
    },
    "6957": {
        "「僕はキャスランを守るので　精一杯だ。\n　詩歌の守り手の相手は　君に頼む。": "Je suis deja a bout de forces pour proteger\nCathlan. Je compte sur toi pour t'occuper du\nElegiac Crablet."
    },
    "6958": {
        "「我は　詩歌の守り手なり。\n　何度でも　相手となろう。": "Je suis l'Elegiac Crablet. Je me mesurerai a\nvous autant de fois qu'il le faudra."
    },
    "6959": {
        "「我は　手かげんはせぬ。\n　存分に　そのチカラを示すがよい！": "Je ne retiendrai pas mes coups. Montre-moi\npleinement ta puissance !"
    },
    "6960": {
        "「王家の血を引きし者よ。\n　そして　その志を受けた　勇気ある者よ。\n　そのチカラを　認めよう。": "A toi, descendant du sang royal, et a toi,\ncourageux porteur de cette volonte. Nous\nreconnaissons ta force."
    },
    "6961": {
        "「願わくば　おぬしが　真に\n　詩歌を継ぎし者となることを　我は望む。": "Je souhaite de tout coeur que tu deviennes\ncelui qui heritera veritablement des chants et\ndes poemes."
    },
    "6962": {
        "「さすがだな　<cs_pchero>君。\n　君がいてくれて　本当に助かった。": "Comme prevu, tu es impressionnant,\n<cs_pchero>kun. Ta presence a vraiment ete\nd'une grande aide."
    },
    "6963": {
        "「詩歌の守り手よ。\n　僕は　ヴェリナードの王子として\n　真に詩歌を継ぐ者になると　約束しよう。": "Gardien des chants, en tant que prince de\nVerinard, je te promets de devenir celui qui\nheritera veritablement des poemes."
    },
    "6964": {
        "「よし……。": "D'accord..."
    },
    "6965": {
        "「これが　刹那の歌か……。": "Voila donc le Chant de l'Instantaneite..."
    },
    "6966": {
        "「おお……。歌が……。\n　歌が　頭の中に流れ込んでくる……。": "Oh... La chanson... La chanson s'ecoule dans\nma tete..."
    },
    "6967": {
        "「……よし　覚えた。": "…Bien, je m'en souviens."
    },
    "6968": {
        "「これで　僕は彼女を救える。\n　彼女のもとへ　急ごう。": "Avec ca, je peux sauver Her. Hatons-nous vers\nelle."
    },
    "6969": {
        "「<cs_pchero>君。\n　君にも　ぜひ　立ち会ってほしい。\n　永遠の地下迷宮まで　来てくれ。": "<cs_pchero> kun. J'aimerais vraiment que tu\nsois present. Viens jusqu'au Labyrinthe de\nl'Eternite."
    },
    "6971": {
        "「いよいよ　彼女を助けることができる。\n　これも　すべて　君のおかげだな。": "Enfin, nous allons pouvoir aider Her. Tout\ncela, c'est grace a toi."
    },
    "6972": {
        "「ここはもう　カギをかける必要はない。\n　さあ　行こうか　<pc>君。": "Ici, il n'est plus necessaire de verrouiller\nla porte. Allez, avancons, <pc>-kun."
    },
    "6973": {
        "「……待たせたな。\n　今すぐ　刹那の歌で　そこから出してあげよう。": "......Je t'ai fait attendre. Je vais\nimmediatement te liberer d'ici avec la Chanson\nde l'Instant."
    },
    "6974": {
        "「ああ　よどんだ時よ　うつろいたまえ。\n　凍りし時よ　溶け合いたまえ。": "Ah, temps stagnant, change de visage. Temps\nglace, fonds et unis-toi."
    },
    "6975": {
        "「時は流れ　うつろいゆくもの。\n　誰にも止めることなど　できはしない。": "Le temps s'ecoule, tout change. Personne ne\npeut l'arreter."
    },
    "6976": {
        "「我が祈り　聞きとどけたまえ。\n　ああ　我が祈り　かなえたまえ……。": "O, ecoute ma priere. Ah, accorde-moi ma\npriere..."
    },
    "6977": {
        "「……さあ　永遠の水よ。消えてなくなれ。": "... Allez, eau eternelle. Disparais."
    },
    "6978": {
        "「…………。": "."
    },
    "6979": {
        "「なぜだ。なぜ　何も起こらない？": "Pourquoi ? Pourquoi rien ne se passe ?"
    },
    "6980": {
        "「もしかしたら　王家の者というだけでは\n　ダメなのかもしれませんわね……。": "Peut-etre que simplement appartenir a la\nfamille royale ne suffit pas..."
    },
    "6981": {
        "「つまり　この国の王になれない\n　男のあんたじゃ　ダメってことだよ！": "En d'autres termes, un homme comme toi, qui ne\npeut pas devenir le roi de ce pays, ca ne va\npas !"
    },
    "6982": {
        "「どういうことだ　キャスラン？": "Que veux-tu dire, Cathlan ?"
    },
    "6983": {
        "「ああ　バカバカしい。\n　女王相手は　ムリっぽかったから\n　あんたに　目をつけたのにさ。": "Ah, ridicule. Je pensais que la reine serait\ntrop difficile a affronter, alors je t'avais\nchoisi comme cible."
    },
    "6984": {
        "「いったい　何を言っている……。": "Qu'est-ce que tu racontes... ?"
    },
    "6985": {
        "「よくお聞き。この永遠の水の中には\n　バサグランデさまという　それはそれは\n　お強い魔物が　封じられているのさ。": "Ecoute bien. Dans cette eau eternelle, un\npuissant demon nomme BasagLMPdono est scelle."
    },
    "6986": {
        "「私は　その封印を解いて差し上げ\n　バサグランデさまと　チカラを合わせて\n　この世界を　支配してやろうとしてたのさ！": "Je comptais briser ce sceau, unir mes forces\navec BasagLMP-sama et ainsi dominer ce monde !"
    },
    "6987": {
        "「バカな……。僕をだましていたのか！？": "Incroyable... Tu m'as trompe !?"
    },
    "6988": {
        "「そういうこと。私は　ただ知っていることを\n　さも占っているように見せかけて\n　あんたに　伝えていただけ。": "C'est ca. Je faisais simplement semblant de\npredire, en te transmettant ce que je savais\ndeja."
    },
    "6989": {
        "「こんな　芝居までしたってのに\n　ボンクラ王子のせいで\n　とんだムダ骨に　なっちまったよ。": "Meme apres avoir monte un tel spectacle, a\ncause de ce prince incompetent, tout cela a\nete vain."
    },
    "6990": {
        "「ほら　責任を取りなっ！！": "Tiens, assume tes responsabilites !!"
    },
    "6991": {
        "「ぐうっ！": "Guh !"
    },
    "6992": {
        "「アハハハハッ　いいザマだよ。\n　お似合いのカップルだ。": "Ahahaha ! Quelle situation ! Vous faites un\ncouple parfait."
    },
    "6993": {
        "「王子が　永遠の水に囚われれば\n　あの冷徹な女王だって　刹那の歌を\n　唄わないわけには　いかないだろうねえ。": "Si le prince est emprisonne dans l'eau\neternelle, meme cette reine impitoyable ne\npourra s'empecher de chanter la chanson<br>ephemere."
    },
    "6994": {
        "「そして　永遠の水の封印は解かれ……\n　バサグランデさまと　私の時代が来るんだわ！\n　アハハハハハッ！！": "Et ainsi, le sceau de l'eau eternelle sera\nbrise... L'ere de BasagLMP-sama et la mienne\nva commencer ! Ahahahahaha !!"
    },
    "6995": {
        "「この王子ひとりじゃ　頼りにならないから\n　手伝いも入れろと　テキトーに占っといたけど\n　あんたは　思ったより役に立ったわねえ。": "Ce prince n'est pas tres fiable tout seul,\nalors j'ai predit au hasard qu'il aurait\nbesoin d'aide. Mais tu t'es revele plus utile<br>que je ne le pensais."
    },
    "6996": {
        "「私と戦うってんなら　やめときなよ。\n　そりゃもう　強いんだから　私は……ん？": "Si tu veux te battre contre moi, je te\nconseille d'y renoncer. Je suis vraiment\nforte, tu sais... Hein ?"
    },
    "6997": {
        "「ギャワンギャワン！！": "Gyaouin Gyaouin !!"
    },
    "6998": {
        "「痛い　痛いっ！": "Aie, aie !"
    },
    "6999": {
        "「あっ。": "Ah."
    },
    "7000": {
        "「オーディス……。": "Odysseus..."
    },
    "7001": {
        "「遅かったか……。\n　よもや　こんなことに　なっているとは。": "Arrivons-nous trop tard... Je n'aurais jamais\nimagine que cela tournerait ainsi."
    },
    "7002": {
        "「そなたは　オーディスの所に\n　出入りしていた旅の者だな。\n　いったい　何があったというのだ？": "Tu es le voyageur qui frequentait Odysseus,\nn'est-ce pas ? Qu'est-ce qui s'est passe\nexactement ?"
    },
    "7003": {
        "「……なんと。この女占い師が\n　王子をだまして　刹那の歌を唄わせたと！": "Comment ?! Cette femme voyante a trompe le\nprince pour lui faire chanter la Chanson de\nl'Instant ?!"
    },
    "7004": {
        "「おろかな……。\n　わらわの言うことを聞かぬから　こうなる。": "Insense… Voila ce qui arrive quand on ne\nm'ecoute pas."
    },
    "7005": {
        "「す　すぐに王子を　助けなくては！": "Je dois immediatement aider le prince !"
    },
    "7006": {
        "「……しかし　刹那の歌は　禁断の歌。": "Cependant, le Chant de l'Instant est un chant\ninterdit."
    },
    "7007": {
        "「私は　ヴェリナードの女王として\n　それを唄うわけには　まいりません……。": "En tant que reine de Velinade, je ne peux pas\nchanter cela..."
    },
    "7008": {
        "「何を迷う　ディオーレ！！": "Qu'est-ce qui te fait hesiter, DiOray !!"
    },
    "7009": {
        "「息子ひとり助けられずして　何が女王か！？": "Si je ne peux meme pas sauver mon propre fils,\nque suis-je en tant que reine ?!"
    },
    "7010": {
        "「あなた……。": "Toi..."
    },
    "7011": {
        "「これまで心を凍らせ　オーディスに\n　つらく当たってきたのは　何のためだ！": "Pourquoi ai-je du endurcir mon coeur et etre si\ndur envers Odys jusque-la ?"
    },
    "7012": {
        "「古き　ならわしを破り　オーディスを\n　次の王にすると　おまえは誓ったのだろう？": "Old king, tu as jure de briser la tradition et\nde faire d'Audis le prochain roi, n'est-ce pas\n?"
    },
    "7013": {
        "「……あなたの言うとおりです。": "Vous avez raison."
    },
    "7014": {
        "「オーディスを助けるため\n　わらわは　刹那の歌を唄いましょう。": "Pour aider Odys, je vais chanter la Chanson de\nl'Instant."
    },
    "7015": {
        "<center>\nああ　よどんだ時よ　うつろいたまえ。\n凍りし時よ　溶け合いたまえ。": "Ah, temps stagnant, change et deviens fluide.\nTemps gele, fonds et unis-toi."
    },
    "7016": {
        "<center>\n時は流れ　うつろいゆくもの。\n誰にも止めることなど　できはしない。": "Le temps s'ecoule et les choses changent.\nPersonne ne peut l'arreter."
    },
    "7017": {
        "<center>\n我が祈り　聞きとどけたまえ。\nああ　我が祈り　かなえたまえ……。": "O, ecoutez ma priere. Ah, exaucez ma priere..."
    },
    "7018": {
        "「む……。私は　何を……？": "Hum... Qu'est-ce que je... ?"
    },
    "7019": {
        "「永遠の水が　なくなってるじゃないのさ！": "L'eau eternelle a disparu !"
    },
    "7020": {
        "「バサグランデさま！\n　今　お迎えに参ります～！！": "BasagLMP-sama ! Nous venons vous accueillir !"
    },
    "7021": {
        "「う　くっ……。": "Ouh... Grr..."
    },
    "7022": {
        "「母上が　刹那の歌を……。\n　僕のために　唄ってくれるなんて。": "Maman va chanter la Chanson de l'Ephemere...\nJuste pour moi."
    },
    "7025": {
        "「なんということを……。\n　このままでは　この地が滅びる……。": "Quel desastre... A ce rythme, cette terre va\nperir..."
    },
    "7026": {
        "「この地が　滅びる……？": "Cette terre va perir... ?"
    },
    "7027": {
        "「……永遠の水の奥には　かつて\n　暴君と呼ばれ　この地を滅ぼさんとした魔物\n　バサグランデが　封じられている。": "...Dans les profondeurs de l'eau eternelle,\nune creature autrefois appelee le tyran, qui\nchercha a devaster cette terre, est scellee.<br>Son nom est BasagLMPde."
    },
    "7028": {
        "「この娘は　バサグランデを\n　封じるために選ばれた　封印の巫女なのだ。\n　それが　この地を禁断の地とした理由だ。": "Cette fille a ete choisie comme pretresse du\nsceau pour sceller Basag LMPD. C'est pour\ncette raison que cette terre est devenue une<br>terre interdite."
    },
    "7029": {
        "「まさか　そんなことが……。\n　キャスランの言ったことは　本当なのか。": "Impossible... Ce que Cathlan a dit est-il vrai\n?"
    },
    "7030": {
        "「ふたりとも！　その話は後だ。\n　今は　バサグランデをなんとかしなければ。　": "Vous deux ! On parlera de ca plus tard. Pour\nl'instant, il faut faire quelque chose a\npropos de BasagLMPde."
    },
    "7031": {
        "「わらわが　責任を取る。\n　その娘に代わって　封印の巫女となり\n　今一度　バサグランデを封じるのだ。　": "Je prendrai la responsabilite. En remplacant\ncette fille, je deviendrai la pretresse du\nsceau et je scellerai a nouveau BasagLMPde."
    },
    "7032": {
        "「私の名は　セーリア。": "Mon nom est Celia."
    },
    "7033": {
        "「あなたが　今の女王なのですね。\n　封印の巫女として　永遠の水に\n　囚われる覚悟が　おありなのですか？": "Vous etes donc la reine actuelle, n'est-ce pas\n? Etes-vous prete a etre emprisonnee dans\nl'eau eternelle en tant que pretresse du sceau<br>?"
    },
    "7034": {
        "「ヴェリナード女王の　誇りにかけて。\n　長きに渡り　この地を守り続けた\n　あなたの犠牲を　ムダにせぬと誓おう。": "Par l'honneur de la Reine de Velinard. Je jure\nde ne pas gacher votre sacrifice, vous qui\navez protege cette terre pendant si longtemps."
    },
    "7035": {
        "「わらわは　ヴェリナード城へ戻る。\n　急ぎ　封印の儀式の用意をしなくては。": "Je retourne au chateau de Verinard. Je dois\npreparer rapidement le rituel de scellement."
    },
    "7036": {
        "「私は　バサグランデの所へ行きます。\n　封印の巫女の役目は　終わっていません。": "Je vais me rendre aupres de BasagLMP. Le role\nde la pretresse du sceau n'est pas encore\ntermine."
    },
    "7037": {
        "「ウデの立つ方と　お見受けしました。\n　あなたのチカラを　貸してください。": "Je vois que vous etes quelqu'un de talentueux.\nJ'aimerais solliciter votre aide."
    },
    "7038": {
        "「僕のせいだ……。\n　そうだ。僕のせいで　母上が……。": "C'est ma faute... Oui, c'est a cause de moi\nque Mere..."
    },
    "7039": {
        "「バサグランデを　なんとかしなくては。": "Je dois absolument faire quelque chose a\npropos de BasagLMPde."
    },
    "7040": {
        "「ああ～ん　愛しの暴君バサグランデさま。\n　ご復活　おめでとうございます～。": "Ahhh, mon cher Tyrant Bogan-sama.\nFelicitations pour votre resurrection~."
    },
    "7041": {
        "「ワタクシ　キャスランと申しますぅ～。\n　一緒に　世界を支配しましょう～。": "Je m'appelle Cathlan~. Dominons le monde\nensemble~."
    },
    "7042": {
        "「もはや　支配など不要！　\n　我が　この世界を滅ぼしてくれるわ！！": "Je n'ai plus besoin de domination ! Je vais\ndetruire ce monde !!"
    },
    "7043": {
        "「完全に　バサグランデの封印が\n　解けてしまったようですね……。": "Il semble que le sceau de BasagLMPD ait ete\ncompletement brise..."
    },
    "7044": {
        "「封印の巫女か……会いたかったぞ。\n　うぬのせいで　我は長き時をムダにした。": "La pretresse du sceau, hein... J'avais hate de\nte rencontrer. A cause de toi, j'ai gaspille\ntant de temps."
    },
    "7045": {
        "「その報いを今こそ　受けるがよいわ！": "Il est temps pour vous de subir les\nconsequences de vos actes !"
    },
    "7046": {
        "「バサグランデを倒すぞ　<cs_pchero>君。\n　君のチカラを　貸してくれ！": "Nous allons vaincre Basag LMPD,\n<cs_pchero>kun. Prete-moi ta force !"
    },
    "7047": {
        "「バサグランデは　さらに強大になっています。\n　このままでは　どんな勇士であろうと\n　勝ち目はないでしょう。": "Basag LMP est devenu encore plus puissant.\nDans cet etat, meme le plus vaillant des heros\nn'aurait aucune chance de victoire."
    },
    "7048": {
        "「しかし　封じることは　かなわずとも\n　私の歌で　そのチカラを抑えることが\n　できるかもしれません。": "Cependant, bien que je ne puisse pas sceller\ncette force, il est possible que je puisse la\ncontenir avec ma chanson."
    },
    "7049": {
        "「変わらぬ思いが　ここにあるなら\n　永遠の時を　過ごせるだろう。": "Si des sentiments immuables resident ici,\nalors nous pourrons passer une eternite\nensemble."
    },
    "7050": {
        "「ぬうっ！？": "Quoi !?"
    },
    "7051": {
        "「鉄の意志が　ここにあるなら\n　決して動かぬ　山となろう。": "Si une volonte de fer reside ici, elle\ndeviendra une montagne inebranlable."
    },
    "7052": {
        "「くかかかかかっ！\n　にぶったか　封印の巫女よ。\n　その程度では　我を止めることはできぬ！": "Kukakakakakak ! Tu as perdu de ta vigueur,\npretresse du sceau. Avec si peu de puissance,\ntu ne peux m'arreter !"
    },
    "7053": {
        "「……くっ。": "...Tss."
    },
    "7054": {
        "<center>\n変わらぬ思いが　ここにあるなら\n永遠の時を　過ごせるだろう。": "Si des sentiments inchanges se trouvent ici,\nnous pourrons passer un temps eternel."
    },
    "7055": {
        "<center>\n鉄の意志が　ここにあるなら\n決して動かぬ　山となろう。": "Si une volonte de fer se trouve ici, elle\ndeviendra une montagne inebranlable."
    },
    "7056": {
        "「母上の声だ……。": "La voix de ma mere..."
    },
    "7057": {
        "<center>\n変わらぬ思いが　ここにあるなら\n永遠の時を　過ごせるだろう。": "Si des sentiments inchanges se trouvent ici,\nnous pourrons passer un temps eternel."
    },
    "7058": {
        "<center>\n鉄の意志が　ここにあるなら\n決して動かぬ　山となろう。": "Si une volonte de fer se trouve ici, elle\ndeviendra une montagne inebranlable."
    },
    "7059": {
        "<center>\nああ　時よ　たたずみたまえ。\n変わらぬように　動かぬように。": "Ah, temps, arrete-toi. Reste immuable, ne\nbouge pas."
    },
    "7060": {
        "<center>\n永遠の時を　過ごせるならば\n他に　望むものはない……。": "Si je pouvais passer un temps eternel, je ne\nsouhaiterais rien d'autre..."
    },
    "7061": {
        "「ぐおああああっ！！": "Guaaaaah !!"
    },
    "7062": {
        "「今です！　バサグランデの動きが\n　にぶっているうちに！！": "C'est maintenant ! Tant que les mouvements de\nBasag LMPD sont ralentis !!"
    },
    "7063": {
        "「おのれ　おのれぇ！\n　我を滅ぼすなど　できぬとしれぇ！！": "Maudits ! Maudits soyez-vous ! Sachez qu'il\nest impossible de me detruire !!"
    },
    "7064": {
        "「<cs_pchero>君　来てくれたか。": "<cs_pchero>kun, tu es venu."
    },
    "7065": {
        "「母上たちの歌だけでは　バサグランデの\n　動きを止めるのが　やっとのようなんだ。": "Il semble que les chants de ma mere et des\nautres ne suffisent qu'a peine a arreter les\nmouvements de BasagLMP."
    },
    "7066": {
        "「今のバサグランデを　封じるのはムリだ。\n　君のチカラを　貸してくれ！": "Il est impossible de sceller le BasagLMP pour\nle moment. Prete-moi ta force !"
    },
    "7067": {
        "「おのれ……。\n　いまいましい　封印の巫女め！": "Maudit sois-tu... maudite pretresse du sceau !"
    },
    "7068": {
        "「むう　息の根を止めそこねたか。\n　封印の巫女の前に　うぬを滅ぼしてくれる！": "Mmh, je n'ai pas reussi a t'achever. Je vais\nte detruire avant que tu n'atteignes la\npretresse du sceau !"
    },
    "7069": {
        "「ぐうぅ……。": "Grrr..."
    },
    "7070": {
        "「我は　世界を滅ぼす者なり……。\n　我が……滅びるなど　ありえぬ！": "Je suis celui qui aneantira le monde... Il est\nimpossible que je... puisse disparaitre !"
    },
    "7071": {
        "「ぐうぅぅあああああっ！！": "Guuuuaaahhhh !!"
    },
    "7072": {
        "「あ……うう？": "Ah... Oooh ?"
    },
    "7073": {
        "「まさか　バサグランデさまが……。": "Je n'aurais jamais imagine que\nBasagLMP-sama..."
    },
    "7074": {
        "「ひ……ひいいぃぃぃ！": "Hi... hiiiieee !"
    },
    "7075": {
        "「……逃げ足の速いやつだ。\n　いずれ　機を見て　捕らえてやる。": "Il est rapide pour fuir. Je finirai par le\ncapturer au moment opportun."
    },
    "7076": {
        "「……ありがとう　<cs_pchero>君。\n　君のおかげで　バサグランデは倒れた。": "...... Merci, <cs_pchero> kun. Grace a toi,\nBasagLMP a ete vaincu."
    },
    "7077": {
        "「もう　封印の巫女は必要ない。\n　母上もセーリアも　救われたんだ。": "Plus besoin de la pretresse du sceau. Mere et\nCelia ont ete sauvees."
    },
    "7078": {
        "「<cs_pchero>殿と　言ったか。\n　こたびのこと　わらわは\n　なんと　礼を述べれば　よいのか。": "<cs_pchero> dono, tu as dit. Je ne sais\ncomment te remercier pour cette fois."
    },
    "7079": {
        "「だが　ひとまずは　城へ帰ろう。\n　もはや　ここに用は　なくなった……。": "Mais pour l'instant, retournons au chateau.\nNous n'avons plus rien a faire ici..."
    },
    "7080": {
        "「セーリア殿。そなたも城へ。\n　話したいことが　山ほどあろう。": "Celia-dono. Toi aussi, viens au chateau. Il y\na tant de choses a discuter."
    },
    "7081": {
        "「どうやら　私の役目も終わったようです……。": "Il semble que mon role soit egalement\ntermine..."
    },
    "7082": {
        "「これから　私が何をすべきか　わかりませんが\n　今は　あなたと共に参りましょう。": "Je ne sais pas encore ce que je dois faire,\nmais pour l'instant, allons ensemble."
    },
    "7083": {
        "「<cs_pchero>君も　城へ来てくれるか？\n　君の願いを　果たさなくてはならないからな。": "<cs_pchero> kun, pourrais-tu venir au chateau\n? Je dois exaucer ton souhait, apres tout."
    },
    "7084": {
        "「<pc>殿　待っていたぞ。\n　こちらへ　参られよ。": "<pc>-dono, je vous attendais. Veuillez\nvenir par ici."
    },
    "7085": {
        "「そなたには　たいへん　世話になった。\n　この国の女王として　礼を言う。": "Tu nous as ete d'une grande aide. En tant que\nreine de ce royaume, je te remercie."
    },
    "7086": {
        "「もし　<pc>殿が\n　いなかったら　どうなっていたのか\n　お前は　わかっているのか　オーディス？": "Si <pc>-dono n'avait pas ete la, sais-tu\nce qui se serait passe, Audis ?"
    },
    "7087": {
        "「はい……。": "Oui..."
    },
    "7088": {
        "「こたびのこと　すべて　お前の\n　独りよがりな行動が　招いたことだ。\n　王家の言い伝えに　背いてな。": "Cette fois-ci, tout est de ta faute, cause par\ntes actions egoistes. Tu as desobei aux\nlegendes de la famille royale."
    },
    "7089": {
        "「言葉もありません……。": "Je suis sans voix..."
    },
    "7090": {
        "「セーリア殿は　封印の巫女となることを\n　自ら　受け入れたのだ。\n　お前に　それを否定する権利はない。": "Celia-dono a elle-meme accepte de devenir la\npretresse du sceau. Tu n'as pas le droit de le\ncontester."
    },
    "7091": {
        "「…………。": "."
    },
    "7092": {
        "「私は　この国に住む　多くのウェディの民を\n　救うために　封印の巫女となりました。": "Je suis devenue la pretresse du sceau pour\nsauver les nombreux Weddies qui habitent ce\npays."
    },
    "7093": {
        "「しかし　王子は　たったひとり……。\n　私を救うためだけに\n　刹那の歌を　唄ってくださいました。": "Pourtant, le prince etait seul... Juste pour\nme sauver, il a chante la Chanson Ephemere."
    },
    "7094": {
        "「そして　女王……\n　あなたがしたことも　それと同じことです。": "Et donc, Reine... Ce que vous avez fait est\nexactement la meme chose."
    },
    "7095": {
        "「そうだ。わらわも同罪だ。\n　息子の命と引き換えに　多くの民の命を\n　危険にさらすことを　いとわなかったのだ。": "Oui, je suis egalement coupable. J'ai ete\nprete a mettre en danger la vie de nombreux\ncitoyens en echange de sauver la vie de mon<br>fils."
    },
    "7096": {
        "「あなた方を責めることは\n　誰にも　できは　しないでしょう。": "Il est impossible pour quiconque de vous\nblamer."
    },
    "7097": {
        "「自分の命よりも大切な　誰かを助けたいと\n　願う気持ち……。私の思いと　あなた方の思いは\n　どちらも　等しいものなのですから。": "Le desir de vouloir sauver quelqu'un qui est\nplus precieux que sa propre vie... Vos\nsentiments et les miens sont tout aussi<br>precieux."
    },
    "7098": {
        "「……その言葉　救われる思いだ。": "Ces mots... me reconfortent."
    },
    "7099": {
        "「この国は　大きな危機から逃れました。\n　ですが　王家の者の役目が　\n　終わったわけでは　ありません。": "Ce pays a echappe a un grand danger.\nCependant, le devoir des membres de la famille\nroyale n'est pas encore termine."
    },
    "7100": {
        "「王は国を治め　それを子が継いでいく。\n　そうやって永遠に　この国をよりよい道へと\n　導いていく責務があるのです。": "Le roi gouverne le royaume, et cet heritage\nest transmis a son enfant. Ainsi,\neternellement, la responsabilite de guider ce<br>pays vers un meilleur chemin incombe a chacun."
    },
    "7101": {
        "「それならば　案じることはない。\n　我が王家には　このオーディスがいる。": "Dans ce cas, il n'y a pas lieu de s'inquieter.\nNous avons Odysse dans notre famille royale."
    },
    "7102": {
        "「母上……。\n　永遠の水の中で聞いた　父上の言葉より\n　僕は　母上の心を知りました。": "Mere... Dans les eaux eternelles, a travers\nles paroles de Pere, j'ai compris le coeur de\nMere."
    },
    "7103": {
        "「それを知らず　勝手なことばかりしていた僕を\n　どうか　お許しください。": "Je vous en prie, pardonnez-moi d'avoir agi\negoistement sans connaitre cela."
    },
    "7104": {
        "「僕は　この国の王になります。\n　ですから　これからも　僕をきたえてください。\n　どんな困難にも　決して負けないように。": "Je deviendrai le roi de ce pays. C'est\npourquoi, continuez a me former. Pour que je\nne perde jamais face a aucune difficulte."
    },
    "7105": {
        "「……よく言った　オーディス。\n　ならば　これからも　厳しくいくとしよう。": "Bien dit, Audis. Dans ce cas, continuons a\netre stricts."
    },
    "7106": {
        "「はい！": "Oui !"
    },
    "7109": {
        "「<pc>君　ありがとう。\n　君には　本当に感謝している。": "<pc>-kun, merci. Je te suis vraiment\nreconnaissant."
    },
    "7110": {
        "「母上。バサグランデを倒した勇士\n　<pc>殿に　我が国のキーエンブレムを\n　授与することを　王子として進言します。": "Mere. En tant que prince, je recommande que\nnous decernions l'embleme cle de notre royaume\na l'heroique <pc>-dono, qui a vaincu<br>BasagLMPde."
    },
    "7111": {
        "「よかろう。<pc>殿　こちらに。": "Tres bien. <pc>-dono, par ici."
    },
    "7112": {
        "「バサグランデ討伐の大任を果たした\n　<pc>殿に　ヴェリナード女王より\n　銀のキーエンブレムを　授けるものとす。": "Pour avoir accompli la grande mission de\nvaincre BasagLMP, <pc>-dono recevra de\nla reine de Verinard l'embleme de la cle<br>d'argent."
    },
    "7113": {
        "<pc>は\n銀のキーエンブレム（だいじなもの）を\n受け取った！<me 72>": "<pc> a recu l'embleme Silver Key (objets\ncles) ! <me 72>"
    },
    "7114": {
        "「僕からの礼として　城下町にある\n　ヴェリナード城駅を　使えるように\n　手配をしておいた。": "En guise de remerciement de ma part, j'ai pris\ndes dispositions pour que vous puissiez\nutiliser la Verinard Castle Station situee<br>dans la ville basse."
    },
    "7115": {
        "「君の旅に　役立つといいんだが……。\n　ただの王子の僕には　こんなことしか\n　できなくて　申し訳ない。": "J'espere que cela sera utile pour ton\nvoyage... Je suis desole, en tant que simple\nprince, c'est tout ce que je peux faire."
    },
    "7116": {
        "「だが　僕は必ず　王になってみせる。\n　だから　君も　自分の目的を果たすため\n　がんばって　旅を続けてくれ！": "Mais je deviendrai roi, c'est certain. Alors,\ntoi aussi, fais de ton mieux pour atteindre\nton objectif et continue ton voyage !"
    },
    "7117": {
        "「旅の者よ。よいところに出てきたな。\n　しばし待たれよ。": "Voyageur. Tu es arrive au bon moment. Attends\nun instant."
    },
    "7118": {
        "「今から　女王ディオーレさまが\n　恵みの歌を　お唄いになられるところだ。\n　旅の記念に　ぜひ聴いていくがよい。": "A present, la Reine Diore va chanter le Chant\nde la Benediction. En souvenir de votre\nvoyage, prenez le temps d'ecouter."
    },
    "7119": {
        "<center>……海に生まれ　海に生きる。\nそれが我ら　ウェディの民。": "...Nes de la mer, vivant pour la mer. Telle\nest la destinee de notre peuple, les Weddie."
    },
    "7120": {
        "<center>母なる海に祈りを捧げ\n我らは求める　神の恵みを。": "Nous prions la mer nourriciere,\nimplorant la benediction des dieux."
    },
    "7121": {
        "<center>大いなる海の神よ。\n我らの命　我らの思い\n守りたまえ　清めたまえ……。": "O grand dieu de la mer. Protege nos vies,\npurifie nos pensees..."
    },
    "7122": {
        "「ああ……。今日の恵みの歌は\n　とっても　優しい感じだったわね……。": "Ah... La chanson de benediction d'aujourd'hui\netait vraiment douce, n'est-ce pas..."
    },
    "7123": {
        "「オーディス王子さまも　にこやかに\n　笑っておられたし　王家の方々に\n　何か　いいことでもあったのかしら？": "Prince Odis-sama souriait aussi joyeusement.\nSe pourrait-il qu'il soit arrive quelque chose\nde bien a la famille royale ?"
    },
    "7124": {
        "「あっ　そうよ　そうだわ！\n　女王さまのとなりにいた　若い女の人！！": "Ah, oui, c'est ca ! La jeune femme qui se\ntenait a cote de la reine !!"
    },
    "7125": {
        "「もしかして　アレかも？\n　王子さまの恋人なのかも！？": "Peut-etre que c'est ca ? Serait-ce la petite\namie du prince !?"
    },
    "7126": {
        "「ということは　あの女の人が\n　次の女王候補ってことじゃない？\n　これは　楽しみね！": "Cela signifie que cette femme est la prochaine\ncandidate au titre de reine, n'est-ce pas ? Ca\npromet d'etre interessant !"
    },
    "7130": {
        "「そうか。それは　ありがたい。": "Je vois. C'est gentil de ta part."
    },
    "7251": {
        "<center>\n母なる海に祈りを捧げ\n我らは求める　神の恵みを。": "Nous prions la mer nourriciere,\nimplorant la benediction des dieux."
    },
    "8908": {
        "「王子さまの見立てに　まちがいないでしょう。\n　この方は　大きなチカラと　なってくれると\n　私も　思いますわ。": "Il n'y a aucun doute dans le jugement du\nprince. Je pense egalement que cette personne\ndeviendra une grande force pour nous."
    },
    "8909": {
        "「最後のシゴトをしてもらうわ。\n　ほら　さっさと　女王を呼んでくんのよ！": "Je veux que tu accomplisses une derniere\ntache. Allez, depeche-toi d'aller chercher la\nreine !"
    },
    "9516": {
        "「テキスト削除": "texte supprimer"
    },
    "9517": {
        "「来てくれたか　<pc>君。": "Tu es venu, <pc>-kun."
    },
    "12225": {
        "「……小生は　何も存じません。": "Je ne sais rien."
    },
    "12226": {
        "「君に迷惑は　かけないと誓う。\n　だから　教えてくれないか？": "Je te promets de ne pas te causer de\nproblemes. Alors, pourrais-tu me le dire ?"
    },
    "12645": {
        "「ですが　僕には　彼女を……セーリアを\n　見捨てることが　できなかったのです。": "Cependant, je ne pouvais pas abandonner Her...\nCelia."
    },
    "27106": {
        "「<pc>君は　遺跡の北側を\n　重点的に　調べてみてくれ。": "<pc>-kun, concentre-toi sur\nl'exploration du cote nord des ruines."
    },
    "31796": {
        "「ランガーオ村の出身なんだな。\n　残念ながら　僕は行ったことがないが\n　よい所だと　聞いている。": "Tu viens du village de Langao, n'est-ce pas ?\nMalheureusement, je n'y suis jamais alle, mais\nj'ai entendu dire que c'est un endroit<br>agreable."
    },
    "31797": {
        "「プクレットの村の出身なんだな。\n　残念ながら　僕は行ったことがないが\n　よい所だと　聞いている。": "Tu viens du village de Pukulet, n'est-ce pas ?\nMalheureusement, je n'y suis jamais alle, mais\nj'ai entendu dire que c'est un endroit<br>agreable."
    },
    "31798": {
        "「ツスクルの村の出身なんだな。\n　残念ながら　僕は行ったことがないが\n　よい所だと　聞いている。": "Tu viens du village de Tsusukul, n'est-ce pas\n? Malheureusement, je n'y suis jamais alle,\nmais j'ai entendu dire que c'est un endroit<br>agreable."
    },
    "31799": {
        "「アグラニの町の出身なんだな。\n　残念ながら　僕は行ったことがないが\n　よい所だと　聞いている。": "Tu viens donc de la ville d'Agrani.\nMalheureusement, je n'y suis jamais alle, mais\nj'ai entendu dire que c'est un endroit<br>agreable."
    },
    "37183": {
        "「うう……。": "Ooh..."
    },
    "37184": {
        "「君！　だいじょうぶか？": "Toi ! Ca va ?"
    },
    "38888": {
        "「なんと　長きに渡り\n　我は　光も届かぬ　暗き水底に\n　押し込められていたことか……。": "Quelle longue periode ai-je passee, enferme\ndans les profondeurs obscures de ces eaux, la\nou la lumiere ne parvient meme pas..."
    }
}
